{
    "bindings": [
        {
            "schedule": "10 * * * *",
            "name": "myTimer",
            "type": "timerTrigger",
            "direction": "in"
        },
        {
            "name": "iamwpRaw",
            "type": "blob",
            "path": "ipps/view-iamwp-raw.json",
            "connection": "wrdsbflenderson_STORAGE",
            "direction": "in"
        },
        {
            "name": "$return",
            "type": "http",
            "direction": "out"
        }
    ],
    "disabled": false
}